navigation_logic.v
module navigation_logic(

input left,
input center,
input right,

output reg warn_left,
output reg warn_center,
output reg warn_right

);

always @(*) begin

warn_left = 0;
warn_center = 0;
warn_right = 0;

if(center)
    warn_center = 1;

else if(left)
    warn_left = 1;

else if(right)
    warn_right = 1;

end

endmodule

navigation_tb.v
`timescale 1ns / 1ps

module navigation_tb;

reg left, center, right;
wire warn_left, warn_center, warn_right;

// Instantiate the logic module
navigation_logic uut (
    .left(left),
    .center(center),
    .right(right),
    .warn_left(warn_left),
    .warn_center(warn_center),
    .warn_right(warn_right)
);

integer f;
integer status;
initial begin
    // Create the waveform file
    $dumpfile("navigation_wave.vcd");
    $dumpvars(0, navigation_tb);

    // Initial state
    left = 0; center = 0; right = 0;
    #10;

    // Read signals from the growing history file
    f = $fopen("navigation_history.txt", "r");
    if (f) begin
        while (!$feof(f)) begin
            status = $fscanf(f, "%d %d %d\n", left, center, right);
            if (status == 3) begin
                #100; // Simulate 100ns for each captured frame
            end
        end
        $fclose(f);
    end

    #10;
    $finish;
end

endmodule

fpga/navigation_wave.vcd
$date
	Fri Apr 24 10:36:10 2026
$end
$version
	Icarus Verilog
$end
$timescale
	1ps
$end
$scope module navigation_tb $end
$var wire 1 ! warn_right $end
$var wire 1 " warn_left $end
$var wire 1 # warn_center $end
$var reg 1 $ center $end
$var reg 1 % left $end
$var reg 1 & right $end
$var integer 32 ' f [31:0] $end
$var integer 32 ( status [31:0] $end
$scope module uut $end
$var wire 1 $ center $end
$var wire 1 % left $end
$var wire 1 & right $end
$var reg 1 # warn_center $end
$var reg 1 " warn_left $end
$var reg 1 ! warn_right $end
$upscope $end
$upscope $end
$enddefinitions $end
#0
$dumpvars
bx (
bx '
0&
0%
0$
0#
0"
0!
$end
#10000
1#
b11 (
1$
b10000000000000000000000000000011 '
#19810000
1"
0#
0$
1%
#20310000
1#
0"
1$
0%
#20510000
1"
0#
0$
1%
#20610000
1#
0"
1$
0%
#30410000
1"
0#
0$
1%
#30510000
1#
0"
1$
0%
#61310000
1"
0#
0$
1%
#61410000
1#
0"
1$
0%
#62010000
1"
0#
0$
1%
#62910000
1#
0"
1$
0%
#63010000
1"
0#
0$
1%
#63310000
1#
0"
1$
0%
#64410000
1"
0#
0$
1%
#64510000
1#
0"
1$
0%
#64710000
1"
0#
0$
1%
#65310000
1#
0"
1$
0%
#65410000
1"
0#
0$
1%
#65610000
1#
0"
1$
0%
#65710000
1"
0#
0$
1%
#65910000
1#
0"
1$
0%
#66010000
1"
0#
0$
1%
#66110000
1#
0"
1$
0%
#66310000
1"
0#
0$
1%
#66410000
1#
0"
1$
0%
#90710000
1"
0#
0$
1%
#91110000
1#
0"
1$
0%
#91210000
1"
0#
0$
1%
#91310000
1#
0"
1$
0%
#93510000
1!
0#
1&
0$
#93610000
1#
0!
0&
1$
#94110000
1!
0#
1&
0$
#94510000
1#
0!
0&
1$
#94710000
1!
0#
1&
0$
#94810000
1#
0!
0&
1$
#95110000
1!
0#
1&
0$
#95210000
1#
0!
0&
1$
#96710000
1!
0#
1&
0$
#97010000
1#
0!
0&
1$
#99010000
1!
0#
1&
0$
#99310000
1"
0!
0&
1%
#99810000
1!
0"
1&
0%
#99910000
1"
0!
0&
1%
#100010000
1#
0"
1$
0%
#100110000
1"
0#
0$
1%
#100210000
1#
0"
1$
0%
#100310000
1!
0#
1&
0$
#100610000
1"
0!
0&
1%
#100710000
1#
0"
1$
0%
#100810000
1!
0#
1&
0$
#100910000
1#
0!
0&
1$
#103310000
1"
0#
0$
1%
#103910000
1#
0"
1$
0%
